{
  "n_val": 6,
  "n_eval": 53,
  "validation_tasks": {
    "instance-0": [
      "silver_gripper",
      "instance-3"
    ],
    "instance-1": [
      "silver_gripper",
      "instance-5"
    ],
    "instance-2": [
      "silver_gripper",
      "instance-6"
    ],
    "instance-3": [
      "silver_gripper",
      "instance-7"
    ],
    "instance-4": [
      "silver_gripper",
      "instance-0"
    ],
    "instance-5": [
      "silver_gripper",
      "instance-2"
    ]
  },
  "eval_tasks": {
    "instance-6": [
      "ipc_gripper98",
      "instance-2"
    ],
    "instance-7": [
      "ipc_gripper98",
      "instance-4"
    ],
    "instance-8": [
      "ipc_gripper98",
      "instance-6"
    ],
    "instance-9": [
      "ipc_gripper98",
      "instance-5"
    ],
    "instance-10": [
      "ipc_gripper98",
      "instance-3"
    ],
    "instance-11": [
      "ipc_gripper98",
      "instance-10"
    ],
    "instance-12": [
      "ipc_gripper98",
      "instance-7"
    ],
    "instance-13": [
      "ipc_gripper98",
      "instance-9"
    ],
    "instance-14": [
      "ipc_gripper98",
      "instance-8"
    ],
    "instance-15": [
      "ipc_gripper98",
      "instance-11"
    ],
    "instance-16": [
      "ipc_gripper98",
      "instance-14"
    ],
    "instance-17": [
      "ipc_gripper98",
      "instance-12"
    ],
    "instance-18": [
      "ipc_gripper98",
      "instance-13"
    ],
    "instance-19": [
      "ipc_gripper98",
      "instance-16"
    ],
    "instance-20": [
      "ipc_gripper98",
      "instance-15"
    ],
    "instance-21": [
      "ipc_gripper98",
      "instance-17"
    ],
    "instance-22": [
      "ipc_gripper98",
      "instance-18"
    ],
    "instance-23": [
      "ipc_gripper98",
      "instance-19"
    ],
    "instance-24": [
      "ipc_gripper98",
      "instance-20"
    ],
    "instance-25": [
      "silver_gripper",
      "instance-19"
    ],
    "instance-26": [
      "silver_gripper",
      "instance-23"
    ],
    "instance-27": [
      "silver_gripper",
      "instance-15"
    ],
    "instance-28": [
      "silver_gripper",
      "instance-35"
    ],
    "instance-29": [
      "silver_gripper",
      "instance-1"
    ],
    "instance-30": [
      "silver_gripper",
      "instance-39"
    ],
    "instance-31": [
      "silver_gripper",
      "instance-38"
    ],
    "instance-32": [
      "silver_gripper",
      "instance-14"
    ],
    "instance-33": [
      "silver_gripper",
      "instance-22"
    ],
    "instance-34": [
      "silver_gripper",
      "instance-34"
    ],
    "instance-35": [
      "silver_gripper",
      "instance-18"
    ],
    "instance-36": [
      "silver_gripper",
      "instance-13"
    ],
    "instance-37": [
      "silver_gripper",
      "instance-29"
    ],
    "instance-38": [
      "silver_gripper",
      "instance-33"
    ],
    "instance-39": [
      "silver_gripper",
      "instance-25"
    ],
    "instance-40": [
      "silver_gripper",
      "instance-24"
    ],
    "instance-41": [
      "silver_gripper",
      "instance-32"
    ],
    "instance-42": [
      "silver_gripper",
      "instance-28"
    ],
    "instance-43": [
      "silver_gripper",
      "instance-12"
    ],
    "instance-44": [
      "silver_gripper",
      "instance-9"
    ],
    "instance-45": [
      "silver_gripper",
      "instance-11"
    ],
    "instance-46": [
      "silver_gripper",
      "instance-27"
    ],
    "instance-47": [
      "silver_gripper",
      "instance-31"
    ],
    "instance-48": [
      "silver_gripper",
      "instance-30"
    ],
    "instance-49": [
      "silver_gripper",
      "instance-4"
    ],
    "instance-50": [
      "silver_gripper",
      "instance-26"
    ],
    "instance-51": [
      "silver_gripper",
      "instance-10"
    ],
    "instance-52": [
      "silver_gripper",
      "instance-8"
    ],
    "instance-53": [
      "silver_gripper",
      "instance-21"
    ],
    "instance-54": [
      "silver_gripper",
      "instance-37"
    ],
    "instance-55": [
      "silver_gripper",
      "instance-17"
    ],
    "instance-56": [
      "silver_gripper",
      "instance-16"
    ],
    "instance-57": [
      "silver_gripper",
      "instance-36"
    ],
    "instance-58": [
      "silver_gripper",
      "instance-20"
    ]
  }
}